maz/__init__.py
maz/compositions/__init__.py
maz/tools/__init__.py
maz-0.0.12.dist-info/LICENSE
maz-0.0.12.dist-info/METADATA
maz-0.0.12.dist-info/WHEEL
maz-0.0.12.dist-info/RECORD
